wpdatabase2/__init__.py
wpdatabase2/__main__.py
wpdatabase2/__version__.py
wpdatabase2/classes/__init__.py
wpdatabase2/classes/connection.py
wpdatabase2/classes/credentials.py
wpdatabase2/classes/database.py
wpdatabase2/classes/secret.py
wpdatabase2/exceptions/__init__.py
wpdatabase2/exceptions/invalid_arguments.py
wpdatabase2/exceptions/invalid_database_name.py
wpdatabase2/exceptions/region_not_known.py
wpdatabase2-0.0.15.dist-info/LICENSE
wpdatabase2-0.0.15.dist-info/METADATA
wpdatabase2-0.0.15.dist-info/WHEEL
wpdatabase2-0.0.15.dist-info/top_level.txt
wpdatabase2-0.0.15.dist-info/RECORD
