Metadata-Version: 2.1
Name: wpdatabase2
Version: 0.0.15
Summary: A Python package that checks and/or sets up a WordPress database.
Home-page: https://github.com/ravensorb/py-wordpress-database
Author: Shawn Anderson
Author-email: sanderson@eye-catcher.com
License: MIT
Platform: UNKNOWN
Classifier: Development Status :: 4 - Beta
Classifier: Environment :: Console
Classifier: Intended Audience :: Developers
Classifier: License :: OSI Approved :: MIT License
Classifier: Natural Language :: English
Classifier: Programming Language :: Python :: 3
Classifier: Operating System :: OS Independent
Classifier: Topic :: Internet :: WWW/HTTP :: Site Management
Requires-Dist: boto3 (>=1.9.0)
Requires-Dist: mysql-connector (>=2.1.0)
Requires-Dist: wpconfigr (<=2.0.0,>=1.0.0)
Provides-Extra: dev
Requires-Dist: autopep8 ; extra == 'dev'
Requires-Dist: coverage ; extra == 'dev'
Requires-Dist: pylint ; extra == 'dev'
